MIPS32_PROCESSOR.v
module MIPS32(clk1, clk2); 
    input clk1, clk2;

    reg [31:0] PC, IF_ID_IR, IF_ID_NPC;
    reg [31:0] ID_EX_IR, ID_EX_NPC, ID_EX_A, ID_EX_B, ID_EX_Imm;
    reg [2:0] ID_EX_type, EX_MEM_type, MEM_WB_type; 
    reg [31:0] EX_MEM_IR, EX_MEM_ALUOUT, EX_MEM_B;
    reg        EX_MEM_cond;
    reg [31:0] MEM_WB_IR, MEM_WB_ALUOUT, MEM_WB_LMD;

    reg [31:0] Reg [0:31];      
    reg [31:0] Memory [0:1024];  

 // instruction OPCODE
    parameter ADD   = 6'b000000, SUB  = 6'b000001, AND  = 6'b000010, OR   = 6'b000011,
              SLT   = 6'b000100, MUL  = 6'b000101, HLT  = 6'b111111, LW   = 6'b001000,
              SW    = 6'b001001, ADDI = 6'b001010, SUBI = 6'b001011, SLTI = 6'b001100,
              BNEQZ = 6'b001101, BEQZ = 6'b001110, XOR  = 6'b001111, NOR  = 6'b010000,
              DIV   = 6'b010001, MOD  = 6'b010010, SLLV = 6'b010011, SRLV = 6'b010100,
              SRA   = 6'b010101;

    parameter RR_ALU = 3'b000, RM_ALU = 3'b001, LOAD = 3'b010, STORE = 3'b011,
              BRANCH = 3'b100, HALT   = 3'b101;

    reg HALTED;
    reg TAKEN_BRANCH;

    //  IF STAGE
    always @(posedge clk1) begin
        if (!HALTED) begin
            if (((EX_MEM_IR[31:26] == BEQZ) && (EX_MEM_cond == 1)) ||
                ((EX_MEM_IR[31:26] == BNEQZ) && (EX_MEM_cond == 0))) begin
                IF_ID_IR     <= #2 Memory[EX_MEM_ALUOUT];
                IF_ID_NPC    <= #2 EX_MEM_ALUOUT + 1;
                PC           <= #2 EX_MEM_ALUOUT + 1;
                TAKEN_BRANCH <= #2 1'b1;
            end 
            else begin
    
                IF_ID_IR     <= #2 Memory[PC];
                IF_ID_NPC    <= #2 PC + 1;
                PC           <= #2 PC + 1;
            end
        end
    end

    //ID STAGE
    always @(posedge clk2) begin
        if (!HALTED) begin
            ID_EX_A    <= #2 (IF_ID_IR[25:21] == 5'b00000) ? 0 : Reg[IF_ID_IR[25:21]];
            ID_EX_B    <= #2 (IF_ID_IR[20:16] == 5'b00000) ? 0 : Reg[IF_ID_IR[20:16]];
            ID_EX_NPC  <= #2 IF_ID_NPC;
            ID_EX_IR   <= #2 IF_ID_IR;
            ID_EX_Imm  <= #2 {{16{IF_ID_IR[15]}}, IF_ID_IR[15:0]}; // Sign-extended

            case (IF_ID_IR[31:26])
                ADD,SUB,AND,OR,SLT,MUL,XOR,NOR,DIV,MOD,SLLV,SRLV,SRA : ID_EX_type <= #2 RR_ALU;
                ADDI, SUBI, SLTI          : ID_EX_type <= #2 RM_ALU;
                LW                        : ID_EX_type <= #2 LOAD;
                SW                        : ID_EX_type <= #2 STORE;
                BEQZ, BNEQZ               : ID_EX_type <= #2 BRANCH;
                HLT                       : ID_EX_type <= #2 HALT;
                default                   : ID_EX_type <= #2 HALT; 
            endcase
        end
    end

    // EX STAGE
    always @(posedge clk1) begin
        if (!HALTED) begin
            EX_MEM_type  <= #2 ID_EX_type;
            EX_MEM_IR    <= #2 ID_EX_IR;
            TAKEN_BRANCH <= #2 0;

            case (ID_EX_type)
                RR_ALU: begin
                    case (ID_EX_IR[31:26])
                        ADD     : EX_MEM_ALUOUT   <= #2 ID_EX_A + ID_EX_B;
                        SUB     : EX_MEM_ALUOUT   <= #2 ID_EX_A - ID_EX_B;
                        AND     : EX_MEM_ALUOUT   <= #2 ID_EX_A & ID_EX_B;
                        OR      : EX_MEM_ALUOUT   <= #2 ID_EX_A | ID_EX_B;
                        SLT     : EX_MEM_ALUOUT   <= #2 (ID_EX_A < ID_EX_B);
                        MUL     : EX_MEM_ALUOUT   <= #2 ID_EX_A * ID_EX_B;
                        XOR     : EX_MEM_ALUOUT   <= #2 ID_EX_A ^ ID_EX_B;
                        NOR     : EX_MEM_ALUOUT   <= #2 ~(ID_EX_A | ID_EX_B);
                        DIV     : EX_MEM_ALUOUT   <= #2 ID_EX_B != 0 ? ID_EX_A / ID_EX_B : 32'hxxxxxxxx;  // check denominator  not equal to zero 
                        MOD     : EX_MEM_ALUOUT   <= #2 ID_EX_B != 0 ? ID_EX_A % ID_EX_B : 32'hxxxxxxxx;
                        SLLV    : EX_MEM_ALUOUT   <= #2 ID_EX_B << ID_EX_A[4:0];
                        SRLV    : EX_MEM_ALUOUT   <= #2 ID_EX_B >> ID_EX_A[4:0];
                        SRA     : EX_MEM_ALUOUT   <= #2 $signed(ID_EX_B) >>> ID_EX_A[4:0];
                       default  : EX_MEM_ALUOUT   <= #2 32'hxxxxxxxx;
                        default : EX_MEM_ALUOUT   <= #2 32'hxxxxxxxx;
                    endcase
                end

                RM_ALU: begin
                    case (ID_EX_IR[31:26])
                        ADDI    : EX_MEM_ALUOUT <= #2 ID_EX_A + ID_EX_Imm;
                        SUBI    : EX_MEM_ALUOUT <= #2 ID_EX_A - ID_EX_Imm;
                        SLTI    : EX_MEM_ALUOUT <= #2 (ID_EX_A < ID_EX_Imm);
                        default : EX_MEM_ALUOUT <= #2 32'hxxxxxxxx;
                    endcase
                end

                LOAD, STORE: begin
                    EX_MEM_ALUOUT <= #2 ID_EX_A + ID_EX_Imm;
                    EX_MEM_B      <= #2 ID_EX_B;
                end

                BRANCH: begin
                    EX_MEM_ALUOUT <= #2 ID_EX_NPC + ID_EX_Imm;
                    EX_MEM_cond   <= #2 (ID_EX_A == 0);
                end
            endcase
        end
    end

    //  MEM STAGE 
    always @(posedge clk2) begin
        if (!HALTED) begin
            MEM_WB_type <= #2 EX_MEM_type;
            MEM_WB_IR   <= #2 EX_MEM_IR;

            case (EX_MEM_type)
                RR_ALU, RM_ALU: MEM_WB_ALUOUT <= #2 EX_MEM_ALUOUT;
                LOAD          : MEM_WB_LMD    <= #2 Memory[EX_MEM_ALUOUT];
                STORE         : if (!TAKEN_BRANCH)
                                    Memory[EX_MEM_ALUOUT] <= #2 EX_MEM_B;
            endcase
        end
    end

    // WB STAGE 
    always @(posedge clk1) begin
        if (!TAKEN_BRANCH) begin
            case (MEM_WB_type)
                RR_ALU : Reg[MEM_WB_IR[15:11]] <= #2 MEM_WB_ALUOUT;
                RM_ALU : Reg[MEM_WB_IR[20:16]] <= #2 MEM_WB_ALUOUT;
                LOAD   : Reg[MEM_WB_IR[20:16]] <= #2 MEM_WB_LMD;
                HALT   : HALTED <= #2 1'b1;
            endcase
        end
    end

endmodule

ADD_THREE_NUMBERS_TB.v
module Testbench_MIPS32;
reg clk1,clk2;
integer k;
MIPS32 mips32(.clk1(clk1),.clk2(clk2));
initial begin
    clk1 = 0 ; clk2 = 0;
    repeat(20)
    begin
        #5 clk1 = 1; #5 clk1 = 0;
        #5 clk2 = 1; #5 clk2 = 0;
    end
end
initial begin
    for(k=0 ; k<31 ; k++)
       mips32.Reg[k] = k;

       mips32.Memory[0] = 32'h2801000a;
       mips32.Memory[1] = 32'h28020014;
       mips32.Memory[2] = 32'h28030019;
       mips32.Memory[3] = 32'h00222000;
       mips32.Memory[4] = 32'h0c373800; // dummy instruction Handling data hazard
       mips32.Memory[5] = 32'h00832800;
       mips32.Memory[6] = 32'hfc000000;

       mips32.HALTED       = 0;
       mips32.PC           = 0;
       mips32.TAKEN_BRANCH = 0;

       #200
       for(k=0; k<6; k++)
       $display ("R%1d =  %2d",k,mips32.Reg[k]);
end
initial begin
    $dumpfile("ADD_THREE_NUMBER.vcd");
    $dumpvars(0,Testbench_MIPS32);
    #350 $finish;
end
endmodule

ADD_THREE_NUMBER.vcd
$date
	Sat Aug 02 19:36:19 2025
$end
$version
	Icarus Verilog
$end
$timescale
	1s
$end
$scope module Testbench_MIPS32 $end
$var reg 1 ! clk1 $end
$var reg 1 " clk2 $end
$var integer 32 # k [31:0] $end
$scope module mips32 $end
$var wire 1 ! clk1 $end
$var wire 1 " clk2 $end
$var parameter 6 $ ADD $end
$var parameter 6 % ADDI $end
$var parameter 6 & AND $end
$var parameter 6 ' BEQZ $end
$var parameter 6 ( BNEQZ $end
$var parameter 3 ) BRANCH $end
$var parameter 6 * DIV $end
$var parameter 3 + HALT $end
$var parameter 6 , HLT $end
$var parameter 3 - LOAD $end
$var parameter 6 . LW $end
$var parameter 6 / MOD $end
$var parameter 6 0 MUL $end
$var parameter 6 1 NOR $end
$var parameter 6 2 OR $end
$var parameter 3 3 RM_ALU $end
$var parameter 3 4 RR_ALU $end
$var parameter 6 5 SLLV $end
$var parameter 6 6 SLT $end
$var parameter 6 7 SLTI $end
$var parameter 6 8 SRA $end
$var parameter 6 9 SRLV $end
$var parameter 3 : STORE $end
$var parameter 6 ; SUB $end
$var parameter 6 < SUBI $end
$var parameter 6 = SW $end
$var parameter 6 > XOR $end
$var reg 32 ? EX_MEM_ALUOUT [31:0] $end
$var reg 32 @ EX_MEM_B [31:0] $end
$var reg 32 A EX_MEM_IR [31:0] $end
$var reg 1 B EX_MEM_cond $end
$var reg 3 C EX_MEM_type [2:0] $end
$var reg 1 D HALTED $end
$var reg 32 E ID_EX_A [31:0] $end
$var reg 32 F ID_EX_B [31:0] $end
$var reg 32 G ID_EX_IR [31:0] $end
$var reg 32 H ID_EX_Imm [31:0] $end
$var reg 32 I ID_EX_NPC [31:0] $end
$var reg 3 J ID_EX_type [2:0] $end
$var reg 32 K IF_ID_IR [31:0] $end
$var reg 32 L IF_ID_NPC [31:0] $end
$var reg 32 M MEM_WB_ALUOUT [31:0] $end
$var reg 32 N MEM_WB_IR [31:0] $end
$var reg 32 O MEM_WB_LMD [31:0] $end
$var reg 3 P MEM_WB_type [2:0] $end
$var reg 32 Q PC [31:0] $end
$var reg 1 R TAKEN_BRANCH $end
$upscope $end
$upscope $end
$enddefinitions $end
$comment Show the parameter values. $end
$dumpall
b1111 >
b1001 =
b1011 <
b1 ;
b11 :
b10100 9
b10101 8
b1100 7
b100 6
b10011 5
b0 4
b1 3
b11 2
b10000 1
b101 0
b10010 /
b1000 .
b10 -
b111111 ,
b101 +
b10001 *
b100 )
b1101 (
b1110 '
b10 &
b1010 %
b0 $
$end
#0
$dumpvars
0R
b0 Q
bx P
bx O
bx N
bx M
bx L
bx K
bx J
bx I
bx H
bx G
bx F
bx E
0D
bx C
xB
bx A
bx @
bx ?
b11111 #
0"
0!
$end
#5
1!
#7
b1 Q
b1 L
b101000000000010000000000001010 K
#10
0!
#15
1"
#17
b1 J
b1010 H
b101000000000010000000000001010 G
b1 I
b1 F
b0 E
#20
0"
#25
1!
#27
b1010 ?
b101000000000010000000000001010 A
b1 C
b10 Q
b10 L
b101000000000100000000000010100 K
#30
0!
#35
1"
#37
b1010 M
b101000000000010000000000001010 N
b1 P
b10100 H
b101000000000100000000000010100 G
b10 I
b10 F
#40
0"
#45
1!
#47
b11 Q
b11 L
b101000000000110000000000011001 K
b10100 ?
b101000000000100000000000010100 A
#50
0!
#55
1"
#57
b11001 H
b101000000000110000000000011001 G
b11 I
b11 F
b10100 M
b101000000000100000000000010100 N
#60
0"
#65
1!
#67
b11001 ?
b101000000000110000000000011001 A
b100 Q
b100 L
b1000100010000000000000 K
#70
0!
#75
1"
#77
b11001 M
b101000000000110000000000011001 N
b0 J
b10000000000000 H
b1000100010000000000000 G
b100 I
b10100 F
b1010 E
#80
0"
#85
1!
#87
b101 Q
b101 L
b1100001101110011100000000000 K
b11110 ?
b1000100010000000000000 A
b0 C
#90
0!
#95
1"
#97
b11100000000000 H
b1100001101110011100000000000 G
b101 I
b10111 F
b11110 M
b1000100010000000000000 N
b0 P
#100
0"
#105
1!
#107
b11111 ?
b1100001101110011100000000000 A
b110 Q
b110 L
b100000110010100000000000 K
#110
0!
#115
1"
#117
b11111 M
b1100001101110011100000000000 N
b10100000000000 H
b100000110010100000000000 G
b110 I
b11001 F
b11110 E
#120
0"
#125
1!
#127
b111 Q
b111 L
b11111100000000000000000000000000 K
b110111 ?
b100000110010100000000000 A
#130
0!
#135
1"
#137
b101 J
b0 H
b11111100000000000000000000000000 G
b111 I
b0 F
b0 E
b110111 M
b100000110010100000000000 N
#140
0"
#145
1!
#147
b11111100000000000000000000000000 A
b101 C
b1000 Q
b1000 L
bx K
#150
0!
#155
1"
#157
b11111100000000000000000000000000 N
b101 P
bx H
bx G
b1000 I
bx F
bx E
#160
0"
#165
1!
#167
b1001 Q
b1001 L
bx A
1D
#170
0!
#175
1"
#180
0"
#185
1!
#190
0!
#195
1"
#200
0"
b110 #
